PHStatsMethods/DSR.py
PHStatsMethods/ISRate.py
PHStatsMethods/ISRatio.py
PHStatsMethods/__init__.py
PHStatsMethods/confidence_intervals.py
PHStatsMethods/funnels.py
PHStatsMethods/means.py
PHStatsMethods/proportions.py
PHStatsMethods/quantiles.py
PHStatsMethods/rates.py
PHStatsMethods/utils.py
PHStatsMethods/utils_funnel.py
PHStatsMethods/validation.py
PHStatsMethods-0.1.12.dist-info/LICENSE.md
PHStatsMethods-0.1.12.dist-info/METADATA
PHStatsMethods-0.1.12.dist-info/WHEEL
PHStatsMethods-0.1.12.dist-info/top_level.txt
PHStatsMethods-0.1.12.dist-info/RECORD
