Metadata-Version: 2.1
Name: PHStatsMethods
Version: 0.1.12
Summary: This is a python package to calculate statistics in public health, including indicators for Fingertips.
Home-page: https://github.com/DataS-DHSC/PHStatsMethods
Author: Department of Health and Social Care
Author-email: annabel.westermann@dhsc.gov.uk, hadley.nanayakkara@dhsc.gov.uk, cameron.stewart@dhsc.gov.uk, jack.burden@dhsc.gov.uk, thilaksan.vikneswaran@dhsc.gov.uk, paul.fryers@dhsc.gov.uk, karandeep.kaur@dhsc.gov.uk, phds@phe.gov.uk
License: GPL-3.0
License-File: LICENSE.md
Requires-Dist: numpy >=1.24.0
Requires-Dist: pandas >=2.0.0
Requires-Dist: pytest >=8.0.0
Requires-Dist: scipy >=1.8.0
Requires-Dist: openpyxl >=3.1.0
